[
    {
        "title" : "Preliminary Design Review",
        "body" : "click link here",
        "date" : "10/03/2017",
        "id" : "001"
    },
    {
        "title" : "Milestone Review Flysheet",
        "body" : "text",
        "date" : "11/03/2017",
        "id" : "002"
    }
    {
        "title" : "Foreign National Form",
        "body" : "text",
        "date" : "11/03/2017",
        "id" : "003"
    }
    {
        "title" : "Presentation for Preliminary Design Review",
        "body" : "text",
        "date" : "11/03/2017",
        "id" : "004"
    }
]
